flownet/__init__.py
flownet/_command_line.py
flownet/ahm/__init__.py
flownet/ahm/_assisted_history_matching.py
flownet/ahm/_run_ahm.py
flownet/config_parser/__init__.py
flownet/config_parser/_config_parser.py
flownet/config_parser/_config_parser_hyperparam.py
flownet/config_parser/_config_parser_pred.py
flownet/config_parser/_config_transformations.py
flownet/config_parser/_merge_configs.py
flownet/data/__init__.py
flownet/data/from_csv.py
flownet/data/from_flow.py
flownet/data/from_pdm.py
flownet/data/from_source.py
flownet/data/perforation_strategy.py
flownet/ert/__init__.py
flownet/ert/_create_ert_setup.py
flownet/ert/_create_synthetic_refcase.py
flownet/ert/_run_subprocess.py
flownet/ert/forward_models/FLOW_SIMULATION
flownet/ert/forward_models/__init__.py
flownet/ert/forward_models/_delete_simulation_output.py
flownet/ert/forward_models/_flow_job.py
flownet/ert/forward_models/_iteration_analytics.py
flownet/ert/forward_models/_render_realization.py
flownet/ert/forward_models/_save_iteration_parameters.py
flownet/ert/forward_models/utils.py
flownet/hyperparameter/__init__.py
flownet/hyperparameter/_run_hyper.py
flownet/network_model/__init__.py
flownet/network_model/_create_egrid.py
flownet/network_model/_generate_connections.py
flownet/network_model/_hull.py
flownet/network_model/_mitchell.py
flownet/network_model/_network_model.py
flownet/network_model/_one_dimensional_model.py
flownet/parameters/__init__.py
flownet/parameters/_aquifer.py
flownet/parameters/_base_parameter.py
flownet/parameters/_equilibration.py
flownet/parameters/_fault_transmissibility.py
flownet/parameters/_permeability.py
flownet/parameters/_porv_poro_trans.py
flownet/parameters/_relative_permeability.py
flownet/parameters/_rock_compressibility.py
flownet/parameters/probability_distributions.py
flownet/prediction/__init__.py
flownet/prediction/_run_pred.py
flownet/realization/__init__.py
flownet/realization/_schedule.py
flownet/realization/_simulation_keywords.py
flownet-0.5.3.dist-info/LICENSE
flownet-0.5.3.dist-info/METADATA
flownet-0.5.3.dist-info/WHEEL
flownet-0.5.3.dist-info/entry_points.txt
flownet-0.5.3.dist-info/top_level.txt
flownet-0.5.3.dist-info/RECORD
