Metadata-Version: 2.1
Name: flownet
Version: 0.5.3
Summary: Simplified training of reservoir simulation models
Home-page: https://github.com/equinor/flownet
Author: R&T Equinor
License: UNKNOWN
Platform: UNKNOWN
Classifier: Programming Language :: Python :: 3
Classifier: Operating System :: OS Independent
Classifier: Natural Language :: English
Classifier: Topic :: Scientific/Engineering
Classifier: License :: OSI Approved :: GNU General Public License v3 (GPLv3)
Requires-Python: ~=3.7
License-File: LICENSE
Requires-Dist: configsuite (>=0.6)
Requires-Dist: cwrap (>=1.6)
Requires-Dist: ecl (>=2.9)
Requires-Dist: ecl2df (>=0.8.1)
Requires-Dist: ert (>=2.17)
Requires-Dist: fmu-ensemble (>=1.2)
Requires-Dist: hyperopt (>=0.2.5)
Requires-Dist: jinja2 (>=2.10)
Requires-Dist: matplotlib (>=3.1)
Requires-Dist: mlflow (>=1.11.0)
Requires-Dist: numpy (>=1.17)
Requires-Dist: opm (>=2020.10)
Requires-Dist: pandas (~=1.0)
Requires-Dist: psutil (>=5.7)
Requires-Dist: pyarrow (>=0.14)
Requires-Dist: pykrige (>=1.5)
Requires-Dist: pyvista (>=0.23)
Requires-Dist: pyyaml (>=5.2)
Requires-Dist: scikit-learn (>=0.22)
Requires-Dist: scipy (>=1.6)
Requires-Dist: webviz-config (>=0.0.42)
Requires-Dist: webviz-config-equinor (>=0.0.9)
Requires-Dist: webviz-subsurface (>=0.0.24)
Requires-Dist: xlrd (<2)
Provides-Extra: tests
Requires-Dist: black ; extra == 'tests'
Requires-Dist: mypy (>=0.761) ; extra == 'tests'
Requires-Dist: pylint (>=2.3) ; extra == 'tests'
Requires-Dist: pyscal (>=0.7.4) ; extra == 'tests'
Requires-Dist: pytest (>=5.3) ; extra == 'tests'
Requires-Dist: pytest-cov (>=2.8) ; extra == 'tests'
Requires-Dist: sphinx ; extra == 'tests'
Requires-Dist: sphinx-rtd-theme ; extra == 'tests'
Requires-Dist: types-pkg-resources ; extra == 'tests'
Requires-Dist: types-PyYAML ; extra == 'tests'
